[{"section_id":"bafkreiaufpr72emgm6gw5bamkomxng3y3v7x6kjxnp4cyalkyqvxj27r6m_sec_1","doc_id":"bafkreiaufpr72emgm6gw5bamkomxng3y3v7x6kjxnp4cyalkyqvxj27r6m","section_num":"1","section_title":"","section_text":"Footnotes:  --- (1) ---\n            \n            Cross reference\u00e2\u20ac\u201d \n               Buildings and building regulations, ch. 14; cable television, ch. 20; public and private roads in subdivisions, \u00c2\u00a7 66-75; traffic and vehicles, ch. 74.\n               \nState Law reference\u00e2\u20ac\u201d \n               Roads and bridges, G.S. 153A-238."}]